polykv/__init__.py
polykv/core.py
polykv-0.1.1.dist-info/licenses/LICENSE
polykv-0.1.1.dist-info/METADATA
polykv-0.1.1.dist-info/WHEEL
polykv-0.1.1.dist-info/top_level.txt
polykv-0.1.1.dist-info/RECORD
