Metadata-Version: 2.4
Name: polykv
Version: 0.1.1
Summary: Native Key-Value Store for Python
Author: PolyKV Team
Project-URL: Homepage, https://github.com/polykv/polykv
Project-URL: Bug Tracker, https://github.com/polykv/polykv/issues
Project-URL: Source, https://github.com/polykv/polykv
Requires-Python: >=3.7
License-File: LICENSE
Requires-Dist: platformdirs>=3.0.0
Dynamic: license-file
